utjls/__init__.py
utjls/azure/__init__.py
utjls/azure/az_authenticate.py
utjls/devops.py
utjls/new_project.py
utjls-0.1.0.dist-info/METADATA
utjls-0.1.0.dist-info/WHEEL
utjls-0.1.0.dist-info/RECORD
